rigid_transform/__init__.py
rigid_transform/transform.py
rigid_transform_py-0.1.1.dist-info/LICENSE
rigid_transform_py-0.1.1.dist-info/METADATA
rigid_transform_py-0.1.1.dist-info/WHEEL
rigid_transform_py-0.1.1.dist-info/top_level.txt
rigid_transform_py-0.1.1.dist-info/RECORD
