Metadata-Version: 2.1
Name: rigid-transform-py
Version: 0.1.1
Summary: Library for Rigid body Transformation.
Home-page: https://github.com/aihalop/rigid-transform-py
Author: Jin Cao
Author-email: aihalop@gmail.com
License: UNKNOWN
Platform: UNKNOWN
Classifier: Programming Language :: Python :: 3
Classifier: License :: OSI Approved :: MIT License
Classifier: Operating System :: OS Independent
Requires-Python: >=3.6
License-File: LICENSE
Requires-Dist: numpy
